LangChaiN/B2.txt
LangChaiN/B3.txt
LangChaiN/B4.txt
LangChaiN/B5.txt
LangChaiN/__init__.py
LangChaiN/core.py
genailib-0.1.5.dist-info/METADATA
genailib-0.1.5.dist-info/WHEEL
genailib-0.1.5.dist-info/top_level.txt
genailib-0.1.5.dist-info/RECORD
